{
  "unversionedId": "michelson/take-away",
  "id": "michelson/take-away",
  "isDocsHomePage": false,
  "title": "Take away",
  "description": "- Smart contracts in Tezos are implemented in the Michelson language which is a stack-based strongly-typed language.",
  "source": "@site/docs/michelson/take-away.md",
  "sourceDirName": "michelson",
  "slug": "/michelson/take-away",
  "permalink": "/michelson/take-away",
  "editUrl": "https://gitlab.com/tezos-paris-hub/OpenTezos/-/blob/main/docs/michelson/take-away.md",
  "version": "current",
  "lastUpdatedBy": "Author",
  "lastUpdatedAt": 1539502055,
  "formattedLastUpdatedAt": "10/14/2018",
  "frontMatter": {
    "id": "take-away",
    "title": "Take away",
    "authors": "Frank Hillard"
  },
  "sidebar": "docs",
  "previous": {
    "title": "Exam",
    "permalink": "/michelson/exam"
  },
  "next": {
    "title": "Introduction",
    "permalink": "/dapp"
  }
}